dagster_chroma/__init__.py
dagster_chroma/config.py
dagster_chroma/resource.py
dagster_chroma-0.0.4.dist-info/METADATA
dagster_chroma-0.0.4.dist-info/WHEEL
dagster_chroma-0.0.4.dist-info/top_level.txt
dagster_chroma-0.0.4.dist-info/RECORD
