Metadata-Version: 2.4
Name: dagster-chroma
Version: 0.0.4
Summary: Dagster integration with chroma
Requires-Python: >=3.10
Requires-Dist: onnxruntime>=1.19.2
Requires-Dist: dagster>=1.8.0
Requires-Dist: chromadb>=0.6.1
